{
  "archetypes": {
    "euphoric": {
      "name": "Эйфорик",
      "description": "Ты видишь мир в ярких красках. Каждый момент наполнен потенциалом.",
      "color": "#FFD700",
      "effects": {
        "text_tone": "optimistic",
        "photo_filter": "warm",
        "audio_pitch": 1.1
      },
      "flavor_texts": {
        "morning": "Новый день — новые возможности!",
        "evening": "Сегодня было прекрасно.",
        "night": "Завтра будет ещё лучше."
      }
    },
    "obsessive": {
      "name": "Обсессив",
      "description": "Ты зацикливаешься на деталях. Мелочи становятся важным.",
      "color": "#9370DB",
      "effects": {
        "text_tone": "detailed",
        "photo_filter": "high_contrast",
        "audio_reverb": 0.3
      },
      "flavor_texts": {
        "morning": "Нужно всё заметить. Всё запомнить.",
        "evening": "Я видел каждую деталь.",
        "night": "Почему я упустил то?"
      }
    },
    "cynic": {
      "name": "Циник",
      "description": "Ты смотришь на мир с подозрением. Ничто не такое, каким кажется.",
      "color": "#708090",
      "effects": {
        "text_tone": "skeptical",
        "photo_filter": "desaturated",
        "audio_lowpass": 0.7
      },
      "flavor_texts": {
        "morning": "Ещё один день. Как все остальные.",
        "evening": "Ничего нового не произошло.",
        "night": "Всё предсказуемо."
      }
    },
    "fleeing": {
      "name": "Беглец",
      "description": "Ты бежишь от моментов. Но они всё равно настигают тебя.",
      "color": "#4682B4",
      "effects": {
        "text_tone": "anxious",
        "photo_filter": "motion_blur",
        "audio_speed": 1.2
      },
      "flavor_texts": {
        "morning": "Надо идти. Быстрее.",
        "evening": "Я убежал. Опять.",
        "night": "От чего я бегу?"
      }
    },
    "healer": {
      "name": "Целитель",
      "description": "Ты ищешь исцеление в каждом встречном. Мир стал мягче.",
      "color": "#98FB98",
      "effects": {
        "text_tone": "gentle",
        "photo_filter": "soft_glow",
        "audio_harmony": 1.0
      },
      "flavor_texts": {
        "morning": "Кому я могу помочь сегодня?",
        "evening": "Я сделал что-то хорошее.",
        "night": "Мир становится лучше."
      }
    },
    "nihilist": {
      "name": "Нигилист",
      "description": "Ничто не имеет значения. И в этом свобода.",
      "color": "#2F4F4F",
      "effects": {
        "text_tone": "detached",
        "photo_filter": "grayscale",
        "audio_silence": 0.2
      },
      "flavor_texts": {
        "morning": "Зачем? Неважно.",
        "evening": "День прошёл. И ладно.",
        "night": "Ничто не длится вечно."
      }
    },
    "selfharm": {
      "name": "Саморазрушитель",
      "description": "Ты причиняешь себе боль снова и снова. Но продолжаешь идти.",
      "color": "#8B0000",
      "effects": {
        "text_tone": "painful",
        "photo_filter": "dark_vignette",
        "audio_distortion": 0.4
      },
      "flavor_texts": {
        "morning": "Больше боли. Больше жизни.",
        "evening": "Я заслужил это.",
        "night": "Завтра будет больнее."
      }
    }
  },
  "lenses": {
    "participation": {
      "name": "Участие",
      "description": "Ты внутри событий. Всё происходит с тобой.",
      "effect": "first_person_text"
    },
    "observation": {
      "name": "Наблюдение",
      "description": "Ты смотришь со стороны. Как камера.",
      "effect": "third_person_text"
    },
    "connection": {
      "name": "Связь",
      "description": "Ты через людей и отношения. Всё связано.",
      "effect": "relational_text"
    }
  }
}
